batch_debugging_cli/__init__.py
batch_debugging_cli/aws_batch_commands.py
batch_debugging_cli/gcp_batch_commands.py
batch_debugging_cli/main.py
batch_debugging_cli/pulumi_commands.py
batch_debugging_cli/seqera_commands.py
batch_debugging_cli-0.0.9.dist-info/METADATA
batch_debugging_cli-0.0.9.dist-info/WHEEL
batch_debugging_cli-0.0.9.dist-info/entry_points.txt
batch_debugging_cli-0.0.9.dist-info/RECORD
