Metadata-Version: 2.1
Name: batch-debugging-cli
Version: 0.0.9
Summary: A CLI that makes it easier to debug issues with batch compute enviornments in AWS, future plans to support GCP, Azure and kubernetes
Author: shahbaz mahmood
Author-email: shahbaz.mahmooood@gmail.com
Requires-Python: >=3.11,<4.0
Classifier: Programming Language :: Python :: 3
Classifier: Programming Language :: Python :: 3.11
Classifier: Programming Language :: Python :: 3.12
Requires-Dist: attrs (>=23.1.0,<24.0.0)
Requires-Dist: batch-debugging (==0.1.5)
Requires-Dist: boto3 (>=1.29.7,<2.0.0)
Requires-Dist: google-cloud-batch (>=0.17.5,<0.18.0)
Requires-Dist: httpx (>=0.25.2,<0.26.0)
Requires-Dist: pulumi (>=3.99.0,<4.0.0)
Requires-Dist: pulumi-gcp (>=7.3.1,<8.0.0)
Requires-Dist: pydantic (>=2.6.1,<3.0.0)
Requires-Dist: pyyaml (>=6.0.1,<7.0.0)
Requires-Dist: typer[all] (>=0.9.0,<0.10.0)
